nextebook_sdk/__init__.py
nextebook_sdk/admin_client.py
nextebook_sdk/client.py
nextebook_sdk/exceptions.py
nextebook_sdk/models.py
nextebook_sdk-1.1.0.dist-info/licenses/LICENSE
nextebook_sdk-1.1.0.dist-info/METADATA
nextebook_sdk-1.1.0.dist-info/WHEEL
nextebook_sdk-1.1.0.dist-info/top_level.txt
nextebook_sdk-1.1.0.dist-info/RECORD
