Metadata-Version: 2.4
Name: nextebook-sdk
Version: 1.1.0
Summary: NextEbook OEM API Python SDK
Home-page: https://github.com/YIZXIY/nextebook-sdk
Author: YIZXIY
Author-email: NextEbook Team <support@nextebook.com>
License: MIT
Project-URL: Homepage, https://github.com/nextebook/nextebook-sdk
Project-URL: Documentation, https://github.com/nextebook/nextebook-sdk#readme
Project-URL: Repository, https://github.com/nextebook/nextebook-sdk.git
Project-URL: Issues, https://github.com/nextebook/nextebook-sdk/issues
Keywords: nextebook,oem,api,sdk,ebook,activation
Classifier: Development Status :: 5 - Production/Stable
Classifier: Intended Audience :: Developers
Classifier: Topic :: Software Development :: Libraries :: Python Modules
Classifier: License :: OSI Approved :: MIT License
Classifier: Programming Language :: Python :: 3
Classifier: Programming Language :: Python :: 3.8
Classifier: Programming Language :: Python :: 3.9
Classifier: Programming Language :: Python :: 3.10
Classifier: Programming Language :: Python :: 3.11
Classifier: Programming Language :: Python :: 3.12
Requires-Python: >=3.8
License-File: LICENSE
Requires-Dist: requests>=2.28.0
Provides-Extra: dev
Requires-Dist: pytest>=7.0.0; extra == "dev"
Requires-Dist: pytest-cov>=4.0.0; extra == "dev"
Requires-Dist: black>=23.0.0; extra == "dev"
Requires-Dist: isort>=5.12.0; extra == "dev"
Requires-Dist: mypy>=1.0.0; extra == "dev"
Dynamic: license-file
